jax_ddp/.DS_Store
jax_ddp/__init__.py
jax_ddp/plants/__init__.py
jax_ddp/plants/nonlinear_model.py
jax_ddp/solvers/__init__.py
jax_ddp/solvers/cost_functions.py
jax_ddp/solvers/ddp.py
jax_ddp-0.1.0.dist-info/WHEEL
jax_ddp-0.1.0.dist-info/METADATA
jax_ddp-0.1.0.dist-info/RECORD
