Metadata-Version: 2.1
Name: jax-ddp
Version: 0.1.0
Summary: 
Author: David Browne
Author-email: davidbrowne@outlook.com
Requires-Python: >=3.8.12,<3.10
Classifier: Programming Language :: Python :: 3
Classifier: Programming Language :: Python :: 3.9
Requires-Dist: jax
Requires-Dist: jaxlib
Requires-Dist: plotly (>=5.1.0,<6.0.0)
Requires-Dist: tqdm
